LICENSE.md
README.md
setup.py
ADLStream2/__init__.py
ADLStream2/adlstream.py
ADLStream2.egg-info/PKG-INFO
ADLStream2.egg-info/SOURCES.txt
ADLStream2.egg-info/dependency_links.txt
ADLStream2.egg-info/requires.txt
ADLStream2.egg-info/top_level.txt
ADLStream2/data/__init__.py
ADLStream2/data/base_stream_generator.py
ADLStream2/data/classification_generator.py
ADLStream2/data/moving_window_generator.py
ADLStream2/data/preprocessing/__init__.py
ADLStream2/data/preprocessing/base_preprocessor.py
ADLStream2/data/preprocessing/mean_normalization_scaler.py
ADLStream2/data/preprocessing/min_max_scaler.py
ADLStream2/data/preprocessing/standardization_scaler.py
ADLStream2/data/stream/__init__.py
ADLStream2/data/stream/base_stream.py
ADLStream2/data/stream/csv_file_stream.py
ADLStream2/data/stream/data_stream.py
ADLStream2/data/stream/fake_stream.py
ADLStream2/data/stream/file_stream.py
ADLStream2/data/stream/kafka_stream.py
ADLStream2/data/stream/river_stream.py
ADLStream2/evaluation/__init__.py
ADLStream2/evaluation/base_evaluator.py
ADLStream2/evaluation/interleaved_chunks.py
ADLStream2/evaluation/metrics.py
ADLStream2/evaluation/prequential.py
ADLStream2/models/__init__.py
ADLStream2/models/cnn.py
ADLStream2/models/ernn.py
ADLStream2/models/esn.py
ADLStream2/models/gru.py
ADLStream2/models/lstm.py
ADLStream2/models/mlp.py
ADLStream2/models/model_factory.py
ADLStream2/models/tcn.py
ADLStream2/models/transformer.py
ADLStream2/utils/__init__.py
ADLStream2/utils/plot_utils.py
ADLStream2/utils/test_utils.py